ffprobe8_binaries/__init__.py
ffprobe8_binaries/binaries/linux/x86_64/ffprobe
ffprobe8_binaries-0.3.dist-info/METADATA
ffprobe8_binaries-0.3.dist-info/WHEEL
ffprobe8_binaries-0.3.dist-info/top_level.txt
ffprobe8_binaries-0.3.dist-info/RECORD
