Metadata-Version: 2.4
Name: ffprobe8-binaries
Version: 0.3
Summary: provide ffprobe 8.0 binaries
Home-page: 
Author: clay
Author-email: clayzz@foxmail.com
Dynamic: author
Dynamic: author-email
Dynamic: summary
